[
  {
    "ContainingType": "HospitalSystem.Controllers.AppointmentController",
    "Method": "Get",
    "RelativePath": "api/Appointment",
    "HttpMethod": "GET",
    "IsController": true,
    "Order": 0,
    "Parameters": [],
    "ReturnTypes": []
  },
  {
    "ContainingType": "HospitalSystem.Controllers.AppointmentController",
    "Method": "Create",
    "RelativePath": "api/Appointment",
    "HttpMethod": "POST",
    "IsController": true,
    "Order": 0,
    "Parameters": [
      {
        "Name": "appointment",
        "Type": "HospitalSystem.DTO.Models.Appointment",
        "IsRequired": true
      }
    ],
    "ReturnTypes": []
  },
  {
    "ContainingType": "HospitalSystem.Controllers.AppointmentController",
    "Method": "Get",
    "RelativePath": "api/Appointment/{id}",
    "HttpMethod": "GET",
    "IsController": true,
    "Order": 0,
    "Parameters": [
      {
        "Name": "id",
        "Type": "System.Int32",
        "IsRequired": true
      }
    ],
    "ReturnTypes": []
  },
  {
    "ContainingType": "HospitalSystem.Controllers.BillController",
    "Method": "GetAll",
    "RelativePath": "api/Bill",
    "HttpMethod": "GET",
    "IsController": true,
    "Order": 0,
    "Parameters": [],
    "ReturnTypes": []
  },
  {
    "ContainingType": "HospitalSystem.Controllers.BillController",
    "Method": "Generate",
    "RelativePath": "api/Bill/{appointmentId}",
    "HttpMethod": "POST",
    "IsController": true,
    "Order": 0,
    "Parameters": [
      {
        "Name": "appointmentId",
        "Type": "System.Int32",
        "IsRequired": true
      }
    ],
    "ReturnTypes": []
  },
  {
    "ContainingType": "HospitalSystem.Controllers.BillController",
    "Method": "Get",
    "RelativePath": "api/Bill/{id}",
    "HttpMethod": "GET",
    "IsController": true,
    "Order": 0,
    "Parameters": [
      {
        "Name": "id",
        "Type": "System.Int32",
        "IsRequired": true
      }
    ],
    "ReturnTypes": []
  },
  {
    "ContainingType": "HospitalSystem.Controllers.DoctorController",
    "Method": "Get",
    "RelativePath": "api/Doctor",
    "HttpMethod": "GET",
    "IsController": true,
    "Order": 0,
    "Parameters": [],
    "ReturnTypes": []
  },
  {
    "ContainingType": "HospitalSystem.Controllers.DoctorController",
    "Method": "Create",
    "RelativePath": "api/Doctor",
    "HttpMethod": "POST",
    "IsController": true,
    "Order": 0,
    "Parameters": [
      {
        "Name": "doctor",
        "Type": "HospitalSystem.DTO.Models.Doctor",
        "IsRequired": true
      }
    ],
    "ReturnTypes": []
  },
  {
    "ContainingType": "HospitalSystem.Controllers.DoctorController",
    "Method": "Update",
    "RelativePath": "api/Doctor",
    "HttpMethod": "PUT",
    "IsController": true,
    "Order": 0,
    "Parameters": [
      {
        "Name": "doctor",
        "Type": "HospitalSystem.DTO.Models.Doctor",
        "IsRequired": true
      }
    ],
    "ReturnTypes": []
  },
  {
    "ContainingType": "HospitalSystem.Controllers.DoctorController",
    "Method": "Get",
    "RelativePath": "api/Doctor/{id}",
    "HttpMethod": "GET",
    "IsController": true,
    "Order": 0,
    "Parameters": [
      {
        "Name": "id",
        "Type": "System.Int32",
        "IsRequired": true
      }
    ],
    "ReturnTypes": []
  },
  {
    "ContainingType": "HospitalSystem.Controllers.DoctorController",
    "Method": "Delete",
    "RelativePath": "api/Doctor/{id}",
    "HttpMethod": "DELETE",
    "IsController": true,
    "Order": 0,
    "Parameters": [
      {
        "Name": "id",
        "Type": "System.Int32",
        "IsRequired": true
      }
    ],
    "ReturnTypes": []
  },
  {
    "ContainingType": "HospitalSystem.Controllers.DoctorController",
    "Method": "GetAvailableDoctors",
    "RelativePath": "api/Doctor/available",
    "HttpMethod": "GET",
    "IsController": true,
    "Order": 0,
    "Parameters": [],
    "ReturnTypes": []
  },
  {
    "ContainingType": "HospitalSystem.Controllers.DoctorController",
    "Method": "Performance",
    "RelativePath": "api/Doctor/performance",
    "HttpMethod": "GET",
    "IsController": true,
    "Order": 0,
    "Parameters": [],
    "ReturnTypes": []
  },
  {
    "ContainingType": "HospitalSystem.Controllers.PatientController",
    "Method": "Get",
    "RelativePath": "api/Patient",
    "HttpMethod": "GET",
    "IsController": true,
    "Order": 0,
    "Parameters": [],
    "ReturnTypes": []
  },
  {
    "ContainingType": "HospitalSystem.Controllers.PatientController",
    "Method": "Create",
    "RelativePath": "api/Patient",
    "HttpMethod": "POST",
    "IsController": true,
    "Order": 0,
    "Parameters": [
      {
        "Name": "patient",
        "Type": "HospitalSystem.DTO.Models.Patient",
        "IsRequired": true
      }
    ],
    "ReturnTypes": []
  },
  {
    "ContainingType": "HospitalSystem.Controllers.PatientController",
    "Method": "Get",
    "RelativePath": "api/Patient/{id}",
    "HttpMethod": "GET",
    "IsController": true,
    "Order": 0,
    "Parameters": [
      {
        "Name": "id",
        "Type": "System.Int32",
        "IsRequired": true
      }
    ],
    "ReturnTypes": []
  },
  {
    "ContainingType": "HospitalSystem.Controllers.PatientController",
    "Method": "Update",
    "RelativePath": "api/Patient/{id}",
    "HttpMethod": "PUT",
    "IsController": true,
    "Order": 0,
    "Parameters": [
      {
        "Name": "id",
        "Type": "System.Int32",
        "IsRequired": true
      },
      {
        "Name": "patient",
        "Type": "HospitalSystem.DTO.Models.Patient",
        "IsRequired": true
      }
    ],
    "ReturnTypes": []
  },
  {
    "ContainingType": "HospitalSystem.Controllers.PatientController",
    "Method": "Delete",
    "RelativePath": "api/Patient/{id}",
    "HttpMethod": "DELETE",
    "IsController": true,
    "Order": 0,
    "Parameters": [
      {
        "Name": "id",
        "Type": "System.Int32",
        "IsRequired": true
      }
    ],
    "ReturnTypes": []
  }
]